{
  "generatedAt": "2026-06-04T15:44:23.945Z",
  "summary": {
    "total": 42,
    "ok": 41,
    "warn": 1,
    "error": 0,
    "published": 41,
    "excluded": 1
  },
  "translation": {
    "attempted": 46,
    "kept": 44,
    "rejected": 2,
    "titleFallback": 5
  },
  "sources": [
    {
      "source": "국토정책Brief",
      "category": "정책",
      "maxItems": 5,
      "itemCount": 5,
      "previousCount": 5,
      "status": "ok",
      "detail": "stable",
      "publish": true,
      "checkedAt": "2026-06-04T15:43:32.119Z"
    },
    {
      "source": "국토이슈리포트",
      "category": "이슈",
      "maxItems": 5,
      "itemCount": 5,
      "previousCount": 5,
      "status": "ok",
      "detail": "stable",
      "publish": true,
      "checkedAt": "2026-06-04T15:43:35.522Z"
    },
    {
      "source": "워킹페이퍼",
      "category": "연구",
      "maxItems": 4,
      "itemCount": 4,
      "previousCount": 4,
      "status": "ok",
      "detail": "stable",
      "publish": true,
      "checkedAt": "2026-06-04T15:43:37.348Z"
    },
    {
      "source": "KDI FOCUS",
      "category": "정책",
      "maxItems": 1,
      "itemCount": 0,
      "previousCount": 0,
      "status": "warn",
      "detail": "empty",
      "publish": false,
      "checkedAt": "2026-06-04T15:43:40.050Z"
    },
    {
      "source": "KDI 연구보고서",
      "category": "연구",
      "maxItems": 4,
      "itemCount": 4,
      "previousCount": 4,
      "status": "ok",
      "detail": "stable",
      "publish": true,
      "checkedAt": "2026-06-04T15:43:46.794Z"
    },
    {
      "source": "자본시장연구원",
      "category": "경제",
      "maxItems": 3,
      "itemCount": 3,
      "previousCount": 3,
      "status": "ok",
      "detail": "stable",
      "publish": true,
      "checkedAt": "2026-06-04T15:43:49.460Z"
    },
    {
      "source": "KIEP",
      "category": "경제",
      "maxItems": 3,
      "itemCount": 3,
      "previousCount": 3,
      "status": "ok",
      "detail": "stable",
      "publish": true,
      "checkedAt": "2026-06-04T15:43:51.549Z"
    },
    {
      "source": "한국은행",
      "category": "경제",
      "maxItems": 3,
      "itemCount": 3,
      "previousCount": 3,
      "status": "ok",
      "detail": "stable",
      "publish": true,
      "checkedAt": "2026-06-04T15:43:53.208Z"
    },
    {
      "source": "Stripe Engineering",
      "category": "개발",
      "maxItems": 2,
      "itemCount": 2,
      "previousCount": 2,
      "status": "ok",
      "detail": "stable",
      "publish": true,
      "checkedAt": "2026-06-04T15:43:53.307Z"
    },
    {
      "source": "토스 테크",
      "category": "개발",
      "maxItems": 2,
      "itemCount": 2,
      "previousCount": 2,
      "status": "ok",
      "detail": "stable",
      "publish": true,
      "checkedAt": "2026-06-04T15:43:56.315Z"
    },
    {
      "source": "네이버 D2",
      "category": "개발",
      "maxItems": 2,
      "itemCount": 2,
      "previousCount": 2,
      "status": "ok",
      "detail": "stable",
      "publish": true,
      "checkedAt": "2026-06-04T15:43:58.350Z"
    },
    {
      "source": "GitHub Engineering",
      "category": "개발",
      "maxItems": 2,
      "itemCount": 2,
      "previousCount": 2,
      "status": "ok",
      "detail": "stable",
      "publish": true,
      "checkedAt": "2026-06-04T15:43:58.408Z"
    },
    {
      "source": "Node.js Blog",
      "category": "개발",
      "maxItems": 1,
      "itemCount": 1,
      "previousCount": 1,
      "status": "ok",
      "detail": "stable",
      "publish": true,
      "checkedAt": "2026-06-04T15:43:58.556Z"
    },
    {
      "source": "Django Blog",
      "category": "개발",
      "maxItems": 1,
      "itemCount": 1,
      "previousCount": 1,
      "status": "ok",
      "detail": "stable",
      "publish": true,
      "checkedAt": "2026-06-04T15:43:58.844Z"
    },
    {
      "source": "Python Insider",
      "category": "개발",
      "maxItems": 1,
      "itemCount": 1,
      "previousCount": 1,
      "status": "ok",
      "detail": "stable",
      "publish": true,
      "checkedAt": "2026-06-04T15:43:58.919Z"
    },
    {
      "source": "pnpm Blog",
      "category": "개발",
      "maxItems": 1,
      "itemCount": 1,
      "previousCount": 1,
      "status": "ok",
      "detail": "stable",
      "publish": true,
      "checkedAt": "2026-06-04T15:43:59.023Z"
    },
    {
      "source": "React Blog",
      "category": "개발",
      "maxItems": 2,
      "itemCount": 2,
      "previousCount": 2,
      "status": "ok",
      "detail": "stable",
      "publish": true,
      "checkedAt": "2026-06-04T15:43:59.103Z"
    },
    {
      "source": "Go Blog",
      "category": "개발",
      "maxItems": 2,
      "itemCount": 2,
      "previousCount": 2,
      "status": "ok",
      "detail": "stable",
      "publish": true,
      "checkedAt": "2026-06-04T15:43:59.267Z"
    },
    {
      "source": "Rust Blog",
      "category": "개발",
      "maxItems": 1,
      "itemCount": 1,
      "previousCount": 1,
      "status": "ok",
      "detail": "stable",
      "publish": true,
      "checkedAt": "2026-06-04T15:43:59.397Z"
    },
    {
      "source": "Kubernetes Blog",
      "category": "개발",
      "maxItems": 1,
      "itemCount": 1,
      "previousCount": 1,
      "status": "ok",
      "detail": "stable",
      "publish": true,
      "checkedAt": "2026-06-04T15:43:59.572Z"
    },
    {
      "source": "AWS Developer",
      "category": "개발",
      "maxItems": 1,
      "itemCount": 1,
      "previousCount": 1,
      "status": "ok",
      "detail": "stable",
      "publish": true,
      "checkedAt": "2026-06-04T15:43:59.783Z"
    },
    {
      "source": "Meta Engineering",
      "category": "개발",
      "maxItems": 1,
      "itemCount": 1,
      "previousCount": 1,
      "status": "ok",
      "detail": "stable",
      "publish": true,
      "checkedAt": "2026-06-04T15:43:59.855Z"
    },
    {
      "source": "Dropbox Tech",
      "category": "개발",
      "maxItems": 1,
      "itemCount": 1,
      "previousCount": 1,
      "status": "ok",
      "detail": "stable",
      "publish": true,
      "checkedAt": "2026-06-04T15:44:00.818Z"
    },
    {
      "source": "Slack Engineering",
      "category": "개발",
      "maxItems": 1,
      "itemCount": 1,
      "previousCount": 1,
      "status": "ok",
      "detail": "stable",
      "publish": true,
      "checkedAt": "2026-06-04T15:44:00.936Z"
    },
    {
      "source": "Svelte Blog",
      "category": "개발",
      "maxItems": 1,
      "itemCount": 1,
      "previousCount": 1,
      "status": "ok",
      "detail": "stable",
      "publish": true,
      "checkedAt": "2026-06-04T15:44:01.169Z"
    },
    {
      "source": "AWS Architecture Blog",
      "category": "개발",
      "maxItems": 2,
      "itemCount": 2,
      "previousCount": 2,
      "status": "ok",
      "detail": "stable",
      "publish": true,
      "checkedAt": "2026-06-04T15:44:01.214Z"
    },
    {
      "source": "Martin Fowler",
      "category": "개발",
      "maxItems": 2,
      "itemCount": 2,
      "previousCount": 2,
      "status": "ok",
      "detail": "stable",
      "publish": true,
      "checkedAt": "2026-06-04T15:44:01.586Z"
    },
    {
      "source": "Cloudflare Architecture",
      "category": "개발",
      "maxItems": 2,
      "itemCount": 2,
      "previousCount": 2,
      "status": "ok",
      "detail": "stable",
      "publish": true,
      "checkedAt": "2026-06-04T15:44:01.935Z"
    },
    {
      "source": "Prometheus Blog",
      "category": "개발",
      "maxItems": 2,
      "itemCount": 2,
      "previousCount": 2,
      "status": "ok",
      "detail": "stable",
      "publish": true,
      "checkedAt": "2026-06-04T15:44:02.111Z"
    },
    {
      "source": "Grafana Blog",
      "category": "개발",
      "maxItems": 2,
      "itemCount": 2,
      "previousCount": 2,
      "status": "ok",
      "detail": "stable",
      "publish": true,
      "checkedAt": "2026-06-04T15:44:02.179Z"
    },
    {
      "source": "OpenTelemetry",
      "category": "개발",
      "maxItems": 2,
      "itemCount": 2,
      "previousCount": 2,
      "status": "ok",
      "detail": "stable",
      "publish": true,
      "checkedAt": "2026-06-04T15:44:02.439Z"
    },
    {
      "source": "arXiv cs.SE",
      "category": "개발",
      "maxItems": 2,
      "itemCount": 2,
      "previousCount": 2,
      "status": "ok",
      "detail": "stable",
      "publish": true,
      "checkedAt": "2026-06-04T15:44:02.581Z"
    },
    {
      "source": "PostgreSQL",
      "category": "개발",
      "maxItems": 1,
      "itemCount": 1,
      "previousCount": 1,
      "status": "ok",
      "detail": "stable",
      "publish": true,
      "checkedAt": "2026-06-04T15:44:02.934Z"
    },
    {
      "source": "St. Louis Fed",
      "category": "경제",
      "maxItems": 2,
      "itemCount": 2,
      "previousCount": 2,
      "status": "ok",
      "detail": "stable",
      "publish": true,
      "checkedAt": "2026-06-04T15:44:03.135Z"
    },
    {
      "source": "NY Fed Liberty Street",
      "category": "경제",
      "maxItems": 2,
      "itemCount": 2,
      "previousCount": 2,
      "status": "ok",
      "detail": "stable",
      "publish": true,
      "checkedAt": "2026-06-04T15:44:03.380Z"
    },
    {
      "source": "FRED Blog",
      "category": "경제",
      "maxItems": 2,
      "itemCount": 2,
      "previousCount": 2,
      "status": "ok",
      "detail": "stable",
      "publish": true,
      "checkedAt": "2026-06-04T15:44:03.448Z"
    },
    {
      "source": "NBER Working Papers",
      "category": "경제",
      "maxItems": 2,
      "itemCount": 2,
      "previousCount": 2,
      "status": "ok",
      "detail": "stable",
      "publish": true,
      "checkedAt": "2026-06-04T15:44:03.781Z"
    },
    {
      "source": "ECB Blog",
      "category": "경제",
      "maxItems": 2,
      "itemCount": 2,
      "previousCount": 2,
      "status": "ok",
      "detail": "stable",
      "publish": true,
      "checkedAt": "2026-06-04T15:44:04.259Z"
    },
    {
      "source": "ECB Press",
      "category": "경제",
      "maxItems": 1,
      "itemCount": 1,
      "previousCount": 1,
      "status": "ok",
      "detail": "stable",
      "publish": true,
      "checkedAt": "2026-06-04T15:44:04.357Z"
    },
    {
      "source": "MMCA",
      "category": "전시",
      "maxItems": 5,
      "itemCount": 5,
      "previousCount": 0,
      "status": "ok",
      "detail": "stable",
      "publish": true,
      "checkedAt": "2026-06-04T15:44:07.197Z"
    },
    {
      "source": "국립중앙박물관",
      "category": "전시",
      "maxItems": 4,
      "itemCount": 4,
      "previousCount": 4,
      "status": "ok",
      "detail": "stable",
      "publish": true,
      "checkedAt": "2026-06-04T15:44:12.510Z"
    },
    {
      "source": "EBS",
      "category": "교양",
      "maxItems": 5,
      "itemCount": 5,
      "previousCount": 5,
      "status": "ok",
      "detail": "stable",
      "publish": true,
      "checkedAt": "2026-06-04T15:44:20.980Z"
    }
  ]
}
