{
  "generatedAt": "2026-06-08T16:19:45.991Z",
  "summary": {
    "total": 42,
    "ok": 42,
    "warn": 0,
    "error": 0,
    "published": 42,
    "excluded": 0
  },
  "translation": {
    "attempted": 46,
    "kept": 44,
    "rejected": 2,
    "titleFallback": 5
  },
  "sources": [
    {
      "source": "국토정책Brief",
      "category": "정책",
      "maxItems": 5,
      "itemCount": 5,
      "previousCount": 5,
      "status": "ok",
      "detail": "stable",
      "publish": true,
      "checkedAt": "2026-06-08T16:18:40.102Z"
    },
    {
      "source": "국토이슈리포트",
      "category": "이슈",
      "maxItems": 5,
      "itemCount": 5,
      "previousCount": 5,
      "status": "ok",
      "detail": "stable",
      "publish": true,
      "checkedAt": "2026-06-08T16:18:42.930Z"
    },
    {
      "source": "워킹페이퍼",
      "category": "연구",
      "maxItems": 4,
      "itemCount": 4,
      "previousCount": 4,
      "status": "ok",
      "detail": "stable",
      "publish": true,
      "checkedAt": "2026-06-08T16:18:45.281Z"
    },
    {
      "source": "KDI FOCUS",
      "category": "정책",
      "maxItems": 1,
      "itemCount": 1,
      "previousCount": 1,
      "status": "ok",
      "detail": "stable",
      "publish": true,
      "checkedAt": "2026-06-08T16:18:52.094Z"
    },
    {
      "source": "KDI 연구보고서",
      "category": "연구",
      "maxItems": 4,
      "itemCount": 4,
      "previousCount": 4,
      "status": "ok",
      "detail": "stable",
      "publish": true,
      "checkedAt": "2026-06-08T16:19:02.662Z"
    },
    {
      "source": "자본시장연구원",
      "category": "경제",
      "maxItems": 3,
      "itemCount": 3,
      "previousCount": 3,
      "status": "ok",
      "detail": "stable",
      "publish": true,
      "checkedAt": "2026-06-08T16:19:05.365Z"
    },
    {
      "source": "KIEP",
      "category": "경제",
      "maxItems": 3,
      "itemCount": 3,
      "previousCount": 3,
      "status": "ok",
      "detail": "stable",
      "publish": true,
      "checkedAt": "2026-06-08T16:19:07.368Z"
    },
    {
      "source": "한국은행",
      "category": "경제",
      "maxItems": 3,
      "itemCount": 3,
      "previousCount": 3,
      "status": "ok",
      "detail": "stable",
      "publish": true,
      "checkedAt": "2026-06-08T16:19:09.604Z"
    },
    {
      "source": "Stripe Engineering",
      "category": "개발",
      "maxItems": 2,
      "itemCount": 2,
      "previousCount": 2,
      "status": "ok",
      "detail": "stable",
      "publish": true,
      "checkedAt": "2026-06-08T16:19:09.945Z"
    },
    {
      "source": "토스 테크",
      "category": "개발",
      "maxItems": 2,
      "itemCount": 2,
      "previousCount": 2,
      "status": "ok",
      "detail": "stable",
      "publish": true,
      "checkedAt": "2026-06-08T16:19:12.109Z"
    },
    {
      "source": "네이버 D2",
      "category": "개발",
      "maxItems": 2,
      "itemCount": 2,
      "previousCount": 2,
      "status": "ok",
      "detail": "stable",
      "publish": true,
      "checkedAt": "2026-06-08T16:19:14.061Z"
    },
    {
      "source": "GitHub Engineering",
      "category": "개발",
      "maxItems": 2,
      "itemCount": 2,
      "previousCount": 2,
      "status": "ok",
      "detail": "stable",
      "publish": true,
      "checkedAt": "2026-06-08T16:19:14.117Z"
    },
    {
      "source": "Node.js Blog",
      "category": "개발",
      "maxItems": 1,
      "itemCount": 1,
      "previousCount": 1,
      "status": "ok",
      "detail": "stable",
      "publish": true,
      "checkedAt": "2026-06-08T16:19:14.270Z"
    },
    {
      "source": "Django Blog",
      "category": "개발",
      "maxItems": 1,
      "itemCount": 1,
      "previousCount": 1,
      "status": "ok",
      "detail": "stable",
      "publish": true,
      "checkedAt": "2026-06-08T16:19:14.554Z"
    },
    {
      "source": "Python Insider",
      "category": "개발",
      "maxItems": 1,
      "itemCount": 1,
      "previousCount": 1,
      "status": "ok",
      "detail": "stable",
      "publish": true,
      "checkedAt": "2026-06-08T16:19:14.650Z"
    },
    {
      "source": "pnpm Blog",
      "category": "개발",
      "maxItems": 1,
      "itemCount": 1,
      "previousCount": 1,
      "status": "ok",
      "detail": "stable",
      "publish": true,
      "checkedAt": "2026-06-08T16:19:14.725Z"
    },
    {
      "source": "React Blog",
      "category": "개발",
      "maxItems": 2,
      "itemCount": 2,
      "previousCount": 2,
      "status": "ok",
      "detail": "stable",
      "publish": true,
      "checkedAt": "2026-06-08T16:19:14.921Z"
    },
    {
      "source": "Go Blog",
      "category": "개발",
      "maxItems": 2,
      "itemCount": 2,
      "previousCount": 2,
      "status": "ok",
      "detail": "stable",
      "publish": true,
      "checkedAt": "2026-06-08T16:19:15.163Z"
    },
    {
      "source": "Rust Blog",
      "category": "개발",
      "maxItems": 1,
      "itemCount": 1,
      "previousCount": 1,
      "status": "ok",
      "detail": "stable",
      "publish": true,
      "checkedAt": "2026-06-08T16:19:15.257Z"
    },
    {
      "source": "Kubernetes Blog",
      "category": "개발",
      "maxItems": 1,
      "itemCount": 1,
      "previousCount": 1,
      "status": "ok",
      "detail": "stable",
      "publish": true,
      "checkedAt": "2026-06-08T16:19:15.460Z"
    },
    {
      "source": "AWS Developer",
      "category": "개발",
      "maxItems": 1,
      "itemCount": 1,
      "previousCount": 1,
      "status": "ok",
      "detail": "stable",
      "publish": true,
      "checkedAt": "2026-06-08T16:19:15.680Z"
    },
    {
      "source": "Meta Engineering",
      "category": "개발",
      "maxItems": 1,
      "itemCount": 1,
      "previousCount": 1,
      "status": "ok",
      "detail": "stable",
      "publish": true,
      "checkedAt": "2026-06-08T16:19:15.793Z"
    },
    {
      "source": "Dropbox Tech",
      "category": "개발",
      "maxItems": 1,
      "itemCount": 1,
      "previousCount": 1,
      "status": "ok",
      "detail": "stable",
      "publish": true,
      "checkedAt": "2026-06-08T16:19:16.588Z"
    },
    {
      "source": "Slack Engineering",
      "category": "개발",
      "maxItems": 1,
      "itemCount": 1,
      "previousCount": 1,
      "status": "ok",
      "detail": "stable",
      "publish": true,
      "checkedAt": "2026-06-08T16:19:17.208Z"
    },
    {
      "source": "Svelte Blog",
      "category": "개발",
      "maxItems": 1,
      "itemCount": 1,
      "previousCount": 1,
      "status": "ok",
      "detail": "stable",
      "publish": true,
      "checkedAt": "2026-06-08T16:19:17.499Z"
    },
    {
      "source": "AWS Architecture Blog",
      "category": "개발",
      "maxItems": 2,
      "itemCount": 2,
      "previousCount": 2,
      "status": "ok",
      "detail": "stable",
      "publish": true,
      "checkedAt": "2026-06-08T16:19:17.588Z"
    },
    {
      "source": "Martin Fowler",
      "category": "개발",
      "maxItems": 2,
      "itemCount": 2,
      "previousCount": 2,
      "status": "ok",
      "detail": "stable",
      "publish": true,
      "checkedAt": "2026-06-08T16:19:17.827Z"
    },
    {
      "source": "Cloudflare Architecture",
      "category": "개발",
      "maxItems": 2,
      "itemCount": 2,
      "previousCount": 2,
      "status": "ok",
      "detail": "stable",
      "publish": true,
      "checkedAt": "2026-06-08T16:19:18.141Z"
    },
    {
      "source": "Prometheus Blog",
      "category": "개발",
      "maxItems": 2,
      "itemCount": 2,
      "previousCount": 2,
      "status": "ok",
      "detail": "stable",
      "publish": true,
      "checkedAt": "2026-06-08T16:19:18.319Z"
    },
    {
      "source": "Grafana Blog",
      "category": "개발",
      "maxItems": 2,
      "itemCount": 2,
      "previousCount": 2,
      "status": "ok",
      "detail": "stable",
      "publish": true,
      "checkedAt": "2026-06-08T16:19:18.423Z"
    },
    {
      "source": "OpenTelemetry",
      "category": "개발",
      "maxItems": 2,
      "itemCount": 2,
      "previousCount": 2,
      "status": "ok",
      "detail": "stable",
      "publish": true,
      "checkedAt": "2026-06-08T16:19:18.626Z"
    },
    {
      "source": "arXiv cs.SE",
      "category": "개발",
      "maxItems": 2,
      "itemCount": 2,
      "previousCount": 2,
      "status": "ok",
      "detail": "stable",
      "publish": true,
      "checkedAt": "2026-06-08T16:19:18.712Z"
    },
    {
      "source": "PostgreSQL",
      "category": "개발",
      "maxItems": 1,
      "itemCount": 1,
      "previousCount": 1,
      "status": "ok",
      "detail": "stable",
      "publish": true,
      "checkedAt": "2026-06-08T16:19:19.235Z"
    },
    {
      "source": "St. Louis Fed",
      "category": "경제",
      "maxItems": 2,
      "itemCount": 2,
      "previousCount": 2,
      "status": "ok",
      "detail": "stable",
      "publish": true,
      "checkedAt": "2026-06-08T16:19:19.388Z"
    },
    {
      "source": "NY Fed Liberty Street",
      "category": "경제",
      "maxItems": 2,
      "itemCount": 2,
      "previousCount": 2,
      "status": "ok",
      "detail": "stable",
      "publish": true,
      "checkedAt": "2026-06-08T16:19:19.621Z"
    },
    {
      "source": "FRED Blog",
      "category": "경제",
      "maxItems": 2,
      "itemCount": 2,
      "previousCount": 2,
      "status": "ok",
      "detail": "stable",
      "publish": true,
      "checkedAt": "2026-06-08T16:19:19.763Z"
    },
    {
      "source": "NBER Working Papers",
      "category": "경제",
      "maxItems": 2,
      "itemCount": 2,
      "previousCount": 2,
      "status": "ok",
      "detail": "stable",
      "publish": true,
      "checkedAt": "2026-06-08T16:19:20.215Z"
    },
    {
      "source": "ECB Blog",
      "category": "경제",
      "maxItems": 2,
      "itemCount": 2,
      "previousCount": 2,
      "status": "ok",
      "detail": "stable",
      "publish": true,
      "checkedAt": "2026-06-08T16:19:20.702Z"
    },
    {
      "source": "ECB Press",
      "category": "경제",
      "maxItems": 1,
      "itemCount": 1,
      "previousCount": 1,
      "status": "ok",
      "detail": "stable",
      "publish": true,
      "checkedAt": "2026-06-08T16:19:20.810Z"
    },
    {
      "source": "MMCA",
      "category": "전시",
      "maxItems": 5,
      "itemCount": 5,
      "previousCount": 5,
      "status": "ok",
      "detail": "stable",
      "publish": true,
      "checkedAt": "2026-06-08T16:19:29.887Z"
    },
    {
      "source": "국립중앙박물관",
      "category": "전시",
      "maxItems": 4,
      "itemCount": 4,
      "previousCount": 4,
      "status": "ok",
      "detail": "stable",
      "publish": true,
      "checkedAt": "2026-06-08T16:19:34.563Z"
    },
    {
      "source": "EBS",
      "category": "교양",
      "maxItems": 5,
      "itemCount": 5,
      "previousCount": 5,
      "status": "ok",
      "detail": "stable",
      "publish": true,
      "checkedAt": "2026-06-08T16:19:44.127Z"
    }
  ]
}
