{
  "generatedAt": "2026-06-02T21:27:29.432Z",
  "summary": {
    "total": 42,
    "ok": 40,
    "warn": 1,
    "error": 1,
    "published": 40,
    "excluded": 2
  },
  "translation": {
    "attempted": 46,
    "kept": 45,
    "rejected": 1,
    "titleFallback": 5
  },
  "sources": [
    {
      "source": "국토정책Brief",
      "category": "정책",
      "maxItems": 5,
      "itemCount": 5,
      "previousCount": 5,
      "status": "ok",
      "detail": "stable",
      "publish": true,
      "checkedAt": "2026-06-02T21:24:04.228Z"
    },
    {
      "source": "국토이슈리포트",
      "category": "이슈",
      "maxItems": 5,
      "itemCount": 5,
      "previousCount": 5,
      "status": "ok",
      "detail": "stable",
      "publish": true,
      "checkedAt": "2026-06-02T21:24:06.713Z"
    },
    {
      "source": "워킹페이퍼",
      "category": "연구",
      "maxItems": 4,
      "itemCount": 4,
      "previousCount": 4,
      "status": "ok",
      "detail": "stable",
      "publish": true,
      "checkedAt": "2026-06-02T21:24:08.058Z"
    },
    {
      "source": "KDI FOCUS",
      "category": "정책",
      "maxItems": 1,
      "itemCount": 0,
      "previousCount": 0,
      "status": "warn",
      "detail": "empty",
      "publish": false,
      "checkedAt": "2026-06-02T21:24:10.349Z"
    },
    {
      "source": "KDI 연구보고서",
      "category": "연구",
      "maxItems": 4,
      "itemCount": 4,
      "previousCount": 4,
      "status": "ok",
      "detail": "stable",
      "publish": true,
      "checkedAt": "2026-06-02T21:24:14.469Z"
    },
    {
      "source": "자본시장연구원",
      "category": "경제",
      "maxItems": 3,
      "itemCount": 3,
      "previousCount": 3,
      "status": "ok",
      "detail": "stable",
      "publish": true,
      "checkedAt": "2026-06-02T21:24:16.141Z"
    },
    {
      "source": "KIEP",
      "category": "경제",
      "maxItems": 3,
      "itemCount": 3,
      "previousCount": 3,
      "status": "ok",
      "detail": "stable",
      "publish": true,
      "checkedAt": "2026-06-02T21:24:32.133Z"
    },
    {
      "source": "한국은행",
      "category": "경제",
      "maxItems": 3,
      "itemCount": 3,
      "previousCount": 3,
      "status": "ok",
      "detail": "stable",
      "publish": true,
      "checkedAt": "2026-06-02T21:24:33.579Z"
    },
    {
      "source": "Stripe Engineering",
      "category": "개발",
      "maxItems": 2,
      "itemCount": 2,
      "previousCount": 2,
      "status": "ok",
      "detail": "stable",
      "publish": true,
      "checkedAt": "2026-06-02T21:24:33.798Z"
    },
    {
      "source": "토스 테크",
      "category": "개발",
      "maxItems": 2,
      "itemCount": 2,
      "previousCount": 2,
      "status": "ok",
      "detail": "stable",
      "publish": true,
      "checkedAt": "2026-06-02T21:24:35.828Z"
    },
    {
      "source": "네이버 D2",
      "category": "개발",
      "maxItems": 2,
      "itemCount": 2,
      "previousCount": 2,
      "status": "ok",
      "detail": "stable",
      "publish": true,
      "checkedAt": "2026-06-02T21:24:37.293Z"
    },
    {
      "source": "GitHub Engineering",
      "category": "개발",
      "maxItems": 2,
      "itemCount": 2,
      "previousCount": 2,
      "status": "ok",
      "detail": "stable",
      "publish": true,
      "checkedAt": "2026-06-02T21:24:37.536Z"
    },
    {
      "source": "Node.js Blog",
      "category": "개발",
      "maxItems": 1,
      "itemCount": 1,
      "previousCount": 1,
      "status": "ok",
      "detail": "stable",
      "publish": true,
      "checkedAt": "2026-06-02T21:24:37.761Z"
    },
    {
      "source": "Django Blog",
      "category": "개발",
      "maxItems": 1,
      "itemCount": 1,
      "previousCount": 1,
      "status": "ok",
      "detail": "stable",
      "publish": true,
      "checkedAt": "2026-06-02T21:24:38.096Z"
    },
    {
      "source": "Python Insider",
      "category": "개발",
      "maxItems": 1,
      "itemCount": 1,
      "previousCount": 1,
      "status": "ok",
      "detail": "stable",
      "publish": true,
      "checkedAt": "2026-06-02T21:24:38.120Z"
    },
    {
      "source": "pnpm Blog",
      "category": "개발",
      "maxItems": 1,
      "itemCount": 1,
      "previousCount": 1,
      "status": "ok",
      "detail": "stable",
      "publish": true,
      "checkedAt": "2026-06-02T21:24:38.159Z"
    },
    {
      "source": "React Blog",
      "category": "개발",
      "maxItems": 2,
      "itemCount": 2,
      "previousCount": 2,
      "status": "ok",
      "detail": "stable",
      "publish": true,
      "checkedAt": "2026-06-02T21:24:38.284Z"
    },
    {
      "source": "Go Blog",
      "category": "개발",
      "maxItems": 2,
      "itemCount": 2,
      "previousCount": 2,
      "status": "ok",
      "detail": "stable",
      "publish": true,
      "checkedAt": "2026-06-02T21:24:38.565Z"
    },
    {
      "source": "Rust Blog",
      "category": "개발",
      "maxItems": 1,
      "itemCount": 1,
      "previousCount": 1,
      "status": "ok",
      "detail": "stable",
      "publish": true,
      "checkedAt": "2026-06-02T21:24:38.609Z"
    },
    {
      "source": "Kubernetes Blog",
      "category": "개발",
      "maxItems": 1,
      "itemCount": 1,
      "previousCount": 1,
      "status": "ok",
      "detail": "stable",
      "publish": true,
      "checkedAt": "2026-06-02T21:24:38.728Z"
    },
    {
      "source": "AWS Developer",
      "category": "개발",
      "maxItems": 1,
      "itemCount": 1,
      "previousCount": 1,
      "status": "ok",
      "detail": "stable",
      "publish": true,
      "checkedAt": "2026-06-02T21:24:38.859Z"
    },
    {
      "source": "Meta Engineering",
      "category": "개발",
      "maxItems": 1,
      "itemCount": 1,
      "previousCount": 1,
      "status": "ok",
      "detail": "stable",
      "publish": true,
      "checkedAt": "2026-06-02T21:24:38.998Z"
    },
    {
      "source": "Dropbox Tech",
      "category": "개발",
      "maxItems": 1,
      "itemCount": 1,
      "previousCount": 1,
      "status": "ok",
      "detail": "stable",
      "publish": true,
      "checkedAt": "2026-06-02T21:24:39.549Z"
    },
    {
      "source": "Slack Engineering",
      "category": "개발",
      "maxItems": 1,
      "itemCount": 1,
      "previousCount": 1,
      "status": "ok",
      "detail": "stable",
      "publish": true,
      "checkedAt": "2026-06-02T21:24:39.646Z"
    },
    {
      "source": "Svelte Blog",
      "category": "개발",
      "maxItems": 1,
      "itemCount": 1,
      "previousCount": 1,
      "status": "ok",
      "detail": "stable",
      "publish": true,
      "checkedAt": "2026-06-02T21:24:39.914Z"
    },
    {
      "source": "AWS Architecture Blog",
      "category": "개발",
      "maxItems": 2,
      "itemCount": 2,
      "previousCount": 2,
      "status": "ok",
      "detail": "stable",
      "publish": true,
      "checkedAt": "2026-06-02T21:24:39.997Z"
    },
    {
      "source": "Martin Fowler",
      "category": "개발",
      "maxItems": 2,
      "itemCount": 2,
      "previousCount": 2,
      "status": "ok",
      "detail": "stable",
      "publish": true,
      "checkedAt": "2026-06-02T21:24:40.558Z"
    },
    {
      "source": "Cloudflare Architecture",
      "category": "개발",
      "maxItems": 2,
      "itemCount": 2,
      "previousCount": 2,
      "status": "ok",
      "detail": "stable",
      "publish": true,
      "checkedAt": "2026-06-02T21:24:41.104Z"
    },
    {
      "source": "Prometheus Blog",
      "category": "개발",
      "maxItems": 2,
      "itemCount": 2,
      "previousCount": 2,
      "status": "ok",
      "detail": "stable",
      "publish": true,
      "checkedAt": "2026-06-02T21:24:41.368Z"
    },
    {
      "source": "Grafana Blog",
      "category": "개발",
      "maxItems": 2,
      "itemCount": 2,
      "previousCount": 2,
      "status": "ok",
      "detail": "stable",
      "publish": true,
      "checkedAt": "2026-06-02T21:24:41.460Z"
    },
    {
      "source": "OpenTelemetry",
      "category": "개발",
      "maxItems": 2,
      "itemCount": 2,
      "previousCount": 2,
      "status": "ok",
      "detail": "stable",
      "publish": true,
      "checkedAt": "2026-06-02T21:24:41.534Z"
    },
    {
      "source": "arXiv cs.SE",
      "category": "개발",
      "maxItems": 2,
      "itemCount": 2,
      "previousCount": 2,
      "status": "ok",
      "detail": "stable",
      "publish": true,
      "checkedAt": "2026-06-02T21:24:41.628Z"
    },
    {
      "source": "PostgreSQL",
      "category": "개발",
      "maxItems": 1,
      "itemCount": 1,
      "previousCount": 1,
      "status": "ok",
      "detail": "stable",
      "publish": true,
      "checkedAt": "2026-06-02T21:24:42.632Z"
    },
    {
      "source": "St. Louis Fed",
      "category": "경제",
      "maxItems": 2,
      "itemCount": 2,
      "previousCount": 2,
      "status": "ok",
      "detail": "stable",
      "publish": true,
      "checkedAt": "2026-06-02T21:24:42.686Z"
    },
    {
      "source": "NY Fed Liberty Street",
      "category": "경제",
      "maxItems": 2,
      "itemCount": 2,
      "previousCount": 2,
      "status": "ok",
      "detail": "stable",
      "publish": true,
      "checkedAt": "2026-06-02T21:24:42.831Z"
    },
    {
      "source": "FRED Blog",
      "category": "경제",
      "maxItems": 2,
      "itemCount": 2,
      "previousCount": 2,
      "status": "ok",
      "detail": "stable",
      "publish": true,
      "checkedAt": "2026-06-02T21:24:43.000Z"
    },
    {
      "source": "NBER Working Papers",
      "category": "경제",
      "maxItems": 2,
      "itemCount": 2,
      "previousCount": 2,
      "status": "ok",
      "detail": "stable",
      "publish": true,
      "checkedAt": "2026-06-02T21:24:43.730Z"
    },
    {
      "source": "ECB Blog",
      "category": "경제",
      "maxItems": 2,
      "itemCount": 2,
      "previousCount": 2,
      "status": "ok",
      "detail": "stable",
      "publish": true,
      "checkedAt": "2026-06-02T21:24:44.377Z"
    },
    {
      "source": "ECB Press",
      "category": "경제",
      "maxItems": 1,
      "itemCount": 1,
      "previousCount": 1,
      "status": "ok",
      "detail": "stable",
      "publish": true,
      "checkedAt": "2026-06-02T21:24:44.538Z"
    },
    {
      "source": "MMCA",
      "category": "전시",
      "maxItems": 5,
      "itemCount": 0,
      "previousCount": 0,
      "status": "error",
      "detail": "fetch-failed",
      "publish": false,
      "error": "Command failed: curl -sL --compressed -A Mozilla/5.0 (compatible; GoodInputsBot/2.0) -X GET -H x-requested-with: XMLHttpRequest https://www.mmca.go.kr/exhibitions/AjaxExhibitionList.do?exhFlag=1&searchExhPlaCd=&searchExhCd=&sort=1&pageIndex=1&exhLangCd=01\n",
      "checkedAt": "2026-06-02T21:27:14.551Z"
    },
    {
      "source": "국립중앙박물관",
      "category": "전시",
      "maxItems": 4,
      "itemCount": 4,
      "previousCount": 4,
      "status": "ok",
      "detail": "stable",
      "publish": true,
      "checkedAt": "2026-06-02T21:27:18.769Z"
    },
    {
      "source": "EBS",
      "category": "교양",
      "maxItems": 5,
      "itemCount": 5,
      "previousCount": 5,
      "status": "ok",
      "detail": "stable",
      "publish": true,
      "checkedAt": "2026-06-02T21:27:26.322Z"
    }
  ]
}
